gatherer/__init__.py
gatherer/db_handler.py
gatherer/f_handler.py
gatherer-0.0.1.dist-info/METADATA
gatherer-0.0.1.dist-info/WHEEL
gatherer-0.0.1.dist-info/top_level.txt
gatherer-0.0.1.dist-info/RECORD
