Metadata-Version: 2.1
Name: gatherer
Version: 0.0.1
Summary: Collects data from multiple MySQL Databases in a multi-tenant architecture
Home-page: UNKNOWN
Author: rexshijaku (Rexhep Shijaku)
Author-email: <rexhepshijaku@gmail.com>
License: UNKNOWN
Keywords: python,mysql,database,collector,gatherer,csv,multi-tenant
Platform: UNKNOWN
Classifier: Development Status :: 1 - Planning
Classifier: Intended Audience :: Developers
Classifier: Programming Language :: Python :: 3
Classifier: Operating System :: Unix
Classifier: Operating System :: MacOS :: MacOS X
Classifier: Operating System :: Microsoft :: Windows
